LICENSE
README.md
setup.py
axa_ds_safeai/__init__.py
axa_ds_safeai/check_explainability.py
axa_ds_safeai/check_fairness.py
axa_ds_safeai/check_robustness.py
axa_ds_safeai/core.py
axa_ds_safeai.egg-info/PKG-INFO
axa_ds_safeai.egg-info/SOURCES.txt
axa_ds_safeai.egg-info/dependency_links.txt
axa_ds_safeai.egg-info/top_level.txt
axa_ds_safeai/util/__init__.py
axa_ds_safeai/util/utils.py