Metadata-Version: 2.1
Name: axa_ds_safeai
Version: 0.1.0
Summary: MODEL AGNOSTIC SAFE AI package to measure risks of AI models WITHOUT CONSIDERING TYPE OF THE MODEL
Author: Golnoosh Babaei
Author-email: <golnoosh.babaei@unipv.it>
Classifier: Development Status :: 1 - Planning
Classifier: Intended Audience :: Developers
Classifier: Programming Language :: Python :: 3
Classifier: Operating System :: Unix
Classifier: Operating System :: MacOS :: MacOS X
Classifier: Operating System :: Microsoft :: Windows
License-File: LICENSE
